langchain_vectara-0.2.0.dist-info/METADATA
langchain_vectara-0.2.0.dist-info/WHEEL
langchain_vectara-0.2.0.dist-info/entry_points.txt
langchain_vectara-0.2.0.dist-info/licenses/LICENSE
langchain_vectara/.env
langchain_vectara/__init__.py
langchain_vectara/tools.py
langchain_vectara/vectorstores.py
langchain_vectara-0.2.0.dist-info/RECORD
