Metadata-Version: 2.1
Name: langchain-vectara
Version: 0.2.0
Summary: An integration package connecting Vectara and LangChain
License: MIT
Project-URL: Source Code, https://github.com/vectara/langchain-vectara/tree/main/libs/vectara
Project-URL: Release Notes, https://github.com/vectara/langchain-vectara/releases
Project-URL: repository, https://github.com/vectara/langchain-vectara
Requires-Python: <3.14,>=3.9
Requires-Dist: langchain-core<1.0.0,>=0.3.34
